asf_search/ASFProduct.py
asf_search/ASFSearchResults.py
asf_search/ASFSession.py
asf_search/ASFStackableProduct.py
asf_search/Pair.py
asf_search/__init__.py
asf_search/exceptions.py
asf_search/ASFSearchOptions/ASFSearchOptions.py
asf_search/ASFSearchOptions/__init__.py
asf_search/ASFSearchOptions/config.py
asf_search/ASFSearchOptions/validator_map.py
asf_search/ASFSearchOptions/validators.py
asf_search/CMR/MissionList.py
asf_search/CMR/__init__.py
asf_search/CMR/datasets.py
asf_search/CMR/field_map.py
asf_search/CMR/subquery.py
asf_search/CMR/translate.py
asf_search/Products/AIRSARProduct.py
asf_search/Products/ALOS2Product.py
asf_search/Products/ALOSProduct.py
asf_search/Products/ARIAS1GUNWProduct.py
asf_search/Products/ERSProduct.py
asf_search/Products/JERSProduct.py
asf_search/Products/NISARProduct.py
asf_search/Products/OPERAS1Product.py
asf_search/Products/RADARSATProduct.py
asf_search/Products/S1BurstProduct.py
asf_search/Products/S1Product.py
asf_search/Products/SEASATProduct.py
asf_search/Products/SIRCProduct.py
asf_search/Products/SMAPProduct.py
asf_search/Products/UAVSARProduct.py
asf_search/Products/__init__.py
asf_search/WKT/RepairEntry.py
asf_search/WKT/__init__.py
asf_search/WKT/validate_wkt.py
asf_search/baseline/__init__.py
asf_search/baseline/calc.py
asf_search/baseline/stack.py
asf_search/constants/BEAMMODE.py
asf_search/constants/DATASET.py
asf_search/constants/FLIGHT_DIRECTION.py
asf_search/constants/INSTRUMENT.py
asf_search/constants/INTERNAL.py
asf_search/constants/PLATFORM.py
asf_search/constants/POLARIZATION.py
asf_search/constants/PRODUCTION_CONFIGURATION.py
asf_search/constants/PRODUCT_TYPE.py
asf_search/constants/RANGE_BANDWIDTH.py
asf_search/constants/__init__.py
asf_search/download/__init__.py
asf_search/download/download.py
asf_search/download/file_download_type.py
asf_search/export/__init__.py
asf_search/export/csv.py
asf_search/export/export_translators.py
asf_search/export/geojson.py
asf_search/export/json.py
asf_search-11.0.2.dist-info/licenses/LICENSE
asf_search-11.0.2.dist-info/METADATA
asf_search-11.0.2.dist-info/WHEEL
asf_search-11.0.2.dist-info/top_level.txt
asf_search-11.0.2.dist-info/RECORD
