Metadata-Version: 2.4
Name: asf_search
Version: 11.0.2
Summary: Python wrapper for ASF's SearchAPI
Home-page: https://github.com/asfadmin/Discovery-asf_search.git
Author: Alaska Satellite Facility Discovery Team
Author-email: uaf-asf-discovery@alaska.edu
License: BSD
Project-URL: Documentation, https://docs.asf.alaska.edu/asf_search/basics/
Classifier: Development Status :: 5 - Production/Stable
Classifier: License :: OSI Approved :: BSD License
Classifier: Operating System :: OS Independent
Classifier: Intended Audience :: Developers
Classifier: Intended Audience :: Science/Research
Classifier: Programming Language :: Python :: 3
Classifier: Programming Language :: Python :: 3 :: Only
Classifier: Programming Language :: Python :: 3.10
Classifier: Programming Language :: Python :: 3.11
Classifier: Programming Language :: Python :: 3.12
Classifier: Topic :: Software Development
Classifier: Topic :: Scientific/Engineering :: Atmospheric Science
Classifier: Topic :: Scientific/Engineering :: GIS
Classifier: Topic :: Scientific/Engineering :: Hydrology
Classifier: Topic :: Utilities
Requires-Python: >=3.10
License-File: LICENSE
Requires-Dist: requests
Requires-Dist: shapely
Requires-Dist: pytz
Requires-Dist: numpy
Requires-Dist: dateparser
Requires-Dist: python-dateutil
Requires-Dist: tenacity>=8.2.2
Provides-Extra: test
Requires-Dist: pytest==8.1.1; extra == "test"
Requires-Dist: pytest-automation==3.0.0; extra == "test"
Requires-Dist: pytest-cov; extra == "test"
Requires-Dist: pytest-xdist; extra == "test"
Requires-Dist: coverage; extra == "test"
Requires-Dist: requests-mock==1.11.0; extra == "test"
Requires-Dist: nbformat; extra == "test"
Requires-Dist: nbconvert; extra == "test"
Requires-Dist: ipykernel; extra == "test"
Provides-Extra: extras
Requires-Dist: remotezip>=0.10.0; extra == "extras"
Requires-Dist: ciso8601; extra == "extras"
Provides-Extra: asf-enumeration
Requires-Dist: asf-enumeration>=0.4.0; extra == "asf-enumeration"
Provides-Extra: coherence
Requires-Dist: pandas; extra == "coherence"
Requires-Dist: zarr; extra == "coherence"
Requires-Dist: s3fs; extra == "coherence"
Requires-Dist: rioxarray; extra == "coherence"
Dynamic: author
Dynamic: author-email
Dynamic: classifier
Dynamic: description
Dynamic: description-content-type
Dynamic: home-page
Dynamic: license
Dynamic: license-file
Dynamic: project-url
Dynamic: provides-extra
Dynamic: requires-dist
Dynamic: requires-python
Dynamic: summary
